radiate/__init__.py
radiate/core.py
radiate/embeddings.py
radiate/ingest.py
radiate/ingest_async.py
radiate/llm.py
radiate/metrics.py
radiate/query.py
radiate/reranker.py
radiate/retrieval.py
radiate_ai-0.1.1.dist-info/METADATA
radiate_ai-0.1.1.dist-info/WHEEL
radiate_ai-0.1.1.dist-info/licenses/LICENSE
radiate_ai-0.1.1.dist-info/RECORD
