Metadata-Version: 2.4
Name: radiate-ai
Version: 0.1.1
Summary: The fastest way to add RAG to any Python app
Project-URL: Homepage, https://github.com/Ganesh-reddy005/radiate-ai
Project-URL: Repository, https://github.com/Ganesh-reddy005/radiate-ai
Project-URL: Bug Reports, https://github.com/Ganesh-reddy005/radiate-ai/issues
Project-URL: Documentation, https://github.com/Ganesh-reddy005/radiate-ai
Author-email: Ganesh Reddy <b.ganesh.reddy.05@gmail.com>
License: MIT
License-File: LICENSE
Keywords: ai,embeddings,llm,ml,openai,rag,retrieval,semantic-search,vector-database
Classifier: Development Status :: 3 - Alpha
Classifier: Intended Audience :: Developers
Classifier: License :: OSI Approved :: MIT License
Classifier: Programming Language :: Python :: 3
Classifier: Programming Language :: Python :: 3.9
Classifier: Programming Language :: Python :: 3.10
Classifier: Programming Language :: Python :: 3.11
Classifier: Programming Language :: Python :: 3.12
Classifier: Topic :: Scientific/Engineering :: Artificial Intelligence
Classifier: Topic :: Software Development :: Libraries :: Python Modules
Requires-Python: >=3.9
Requires-Dist: openai>=1.0.0
Requires-Dist: pypdf2>=3.0.0
Requires-Dist: python-dotenv>=1.0.0
Requires-Dist: qdrant-client>=1.7.0
Requires-Dist: tiktoken>=0.5.0
Provides-Extra: all
Requires-Dist: sentence-transformers>=2.2.0; extra == 'all'
Requires-Dist: torch>=2.0.0; extra == 'all'
Requires-Dist: tqdm>=4.66.0; extra == 'all'
Provides-Extra: dev
Requires-Dist: black>=23.0.0; extra == 'dev'
Requires-Dist: flake8>=6.0.0; extra == 'dev'
Requires-Dist: pytest-asyncio>=0.21.0; extra == 'dev'
Requires-Dist: pytest>=7.0.0; extra == 'dev'
Provides-Extra: local
Requires-Dist: sentence-transformers>=2.2.0; extra == 'local'
Requires-Dist: torch>=2.0.0; extra == 'local'
Requires-Dist: tqdm>=4.66.0; extra == 'local'
